funwithconsole/__init__.py
funwithconsole/funwithconsole.py
funwithconsole-1.3.dist-info/LICENSE
funwithconsole-1.3.dist-info/METADATA
funwithconsole-1.3.dist-info/WHEEL
funwithconsole-1.3.dist-info/top_level.txt
funwithconsole-1.3.dist-info/RECORD
