Metadata-Version: 2.1
Name: funwithconsole
Version: 1.3
Summary: funny console tools
Home-page: https://github.com/cccaaannn/funwithconsole
Author: Can Kurt
Author-email: can.kurt.aa@gmail.com
License: UNKNOWN
Platform: UNKNOWN
Classifier: Programming Language :: Python :: 3
Classifier: License :: OSI Approved :: MIT License
Classifier: Operating System :: OS Independent
